{"id":"B5","title":"岩兰草精油乳液（面部、油性肌肤）100ml","subtitle":"玫瑰纯露配合岩兰草精油、薰衣草精油杀菌、治疗粉刺痤疮、镇静、改善油性肌肤","pimgs":["images/item/b5_MG_1588.jpg","images/item/b5_MG_1642.jpg","images/item/b5_MG_1643.jpg","images/item/b5_MG_1645.jpg","images/item/b5_MG_1660.jpg","images/item/b5_MG_1661.jpg","images/item/b5_MG_1662.jpg","images/item/b5_MG_1663.jpg"],"price":220,"use":"清洁后，取本品于使用部位轻轻拍打并按摩至吸收为止<br>怀孕初期避免使用。","element":"大马士革玫瑰纯露+岩兰草精油+薰衣草精油","effect":"质地轻爽舒润不油腻，温和渗透，多种植物本草精华使面部肌肤皮脂分泌趋于平衡，改善脸部油光现象。","rels":[{"id":"B4","pname":"玫瑰精油乳液（面部、干性肌肤）100ml","pimg":"images/itemlist/B4.jpg"},{"id":"B6","pname":"花梨木精油乳液（面部、敏感肌肤）100ml","pimg":"images/itemlist/B6.jpg"},{"id":"D1","pname":"玫瑰精油乳液面膜 25ml","pimg":"images/itemlist/D1.jpg"}]}